{
  "name": "taigaTrigger",
  "displayName": "Taiga Trigger",
  "description": "Handle Taiga events via webhook",
  "group": [
    "trigger"
  ],
  "version": 1,
  "defaults": {
    "projectId": "",
    "resources": [
      "all"
    ],
    "operations": [
      "all"
    ]
  },
  "inputs": [],
  "outputs": [
    "main"
  ],
  "properties": [
    {
      "name": "projectId",
      "displayName": "Project Name or ID",
      "type": "options",
      "default": "",
      "required": true,
      "description": "Choose from the list, or specify an ID using an <a href=\"https://docs.n8n.io/code/expressions/\">expression</a>",
      "typeOptions": {
        "loadOptionsMethod": "getUserProjects"
      }
    },
    {
      "name": "resources",
      "displayName": "Resources",
      "type": "multiOptions",
      "default": [
        "all"
      ],
      "required": true,
      "description": "Resources to listen to",
      "options": [
        {
          "name": "All",
          "value": "all"
        },
        {
          "name": "Issue",
          "value": "issue"
        },
        {
          "name": "Milestone (Sprint)",
          "value": "milestone"
        },
        {
          "name": "Task",
          "value": "task"
        },
        {
          "name": "User Story",
          "value": "userstory"
        },
        {
          "name": "Wikipage",
          "value": "wikipage"
        }
      ]
    },
    {
      "name": "operations",
      "displayName": "Operations",
      "type": "multiOptions",
      "default": [
        "all"
      ],
      "required": true,
      "description": "Operations to listen to",
      "options": [
        {
          "name": "All",
          "value": "all"
        },
        {
          "name": "Create",
          "value": "create"
        },
        {
          "name": "Delete",
          "value": "delete"
        },
        {
          "name": "Update",
          "value": "change"
        }
      ]
    }
  ],
  "credentials": [
    {
      "name": "taigaApi",
      "required": true
    }
  ],
  "hasVersions": false
}