{
  "name": "s3",
  "displayName": "S3",
  "properties": [
    {
      "name": "endpoint",
      "type": "string",
      "default": ""
    },
    {
      "name": "region",
      "type": "string",
      "default": "us-east-1"
    },
    {
      "name": "accessKeyId",
      "type": "string",
      "default": ""
    },
    {
      "name": "secretAccessKey",
      "type": "string",
      "default": ""
    },
    {
      "name": "forcePathStyle",
      "type": "boolean",
      "default": false
    },
    {
      "name": "ignoreSSLIssues",
      "type": "boolean",
      "default": false
    }
  ]
}